sparkformers/__init__.py
sparkformers/sparkformer.py
sparkformers/utils/__init__.py
sparkformers/utils/hf_utils.py
sparkformers/utils/rdd_utils.py
sparkformers/utils/torch_utils.py
sparkformers-0.4.0.dist-info/METADATA
sparkformers-0.4.0.dist-info/WHEEL
sparkformers-0.4.0.dist-info/licenses/LICENSE
sparkformers-0.4.0.dist-info/RECORD
