Metadata-Version: 2.4
Name: sparkformers
Version: 0.4.0
Summary: Distributed deep learning for Hugging Face Transformers on Spark
Author-email: Daniel Cahall <danielenricocahall@gmail.com>
License: MIT
License-File: LICENSE
Requires-Python: <3.13,>3.9
Requires-Dist: pyspark<=4.0.0
Requires-Dist: torch>=2.7.1
Requires-Dist: transformers<5.0.0
